{
  "url": "https://en.wikipedia.org/wiki/2019\u201320_Armenian_Premier_League",
  "title": "2019\u201320 Armenian Premier League",
  "header": [
    [
      [
        "Club"
      ],
      [
        null
      ]
    ],
    [
      [
        "Location"
      ],
      [
        null
      ]
    ],
    [
      [
        "Stadium"
      ],
      [
        null
      ]
    ],
    [
      [
        "Capacity"
      ],
      [
        null
      ]
    ]
  ],
  "data": [
    [
      [
        [
          "Alashkert"
        ],
        [
          "/wiki/FC_Alashkert"
        ]
      ],
      [
        [
          "Yerevan",
          "Shengavit"
        ],
        [
          "/wiki/Yerevan",
          "/wiki/Shengavit_District"
        ]
      ],
      [
        [
          "Alashkert Stadium"
        ],
        [
          "/wiki/Alashkert_Stadium"
        ]
      ],
      [
        [
          "6,850"
        ],
        [
          null
        ]
      ]
    ],
    [
      [
        [
          "Ararat"
        ],
        [
          "/wiki/FC_Ararat_Yerevan"
        ]
      ],
      [
        [
          "Yerevan",
          "Kentron"
        ],
        [
          "/wiki/Yerevan",
          "/wiki/Kentron_District"
        ]
      ],
      [
        [
          "Vazgen Sargsyan Stadium"
        ],
        [
          "/wiki/Vazgen_Sargsyan_Republican_Stadium"
        ]
      ],
      [
        [
          "14,403"
        ],
        [
          null
        ]
      ]
    ],
    [
      [
        [
          "Ararat-Armenia"
        ],
        [
          "/wiki/FC_Ararat-Armenia"
        ]
      ],
      [
        [
          "Yerevan",
          "Avan"
        ],
        [
          "/wiki/Yerevan",
          "/wiki/Avan_District"
        ]
      ],
      [
        [
          "Yerevan Football Academy Stadium"
        ],
        [
          "/wiki/Yerevan_Football_Academy_Stadium"
        ]
      ],
      [
        [
          "1,428"
        ],
        [
          null
        ]
      ]
    ],
    [
      [
        [
          "Gandzasar"
        ],
        [
          "/wiki/FC_Gandzasar_Kapan"
        ]
      ],
      [
        [
          "Yerevan",
          "Avan"
        ],
        [
          "/wiki/Yerevan",
          "/wiki/Avan_District"
        ]
      ],
      [
        [
          "Yerevan Football Academy Stadium"
        ],
        [
          "/wiki/Yerevan_Football_Academy_Stadium"
        ]
      ],
      [
        [
          "1,428"
        ],
        [
          null
        ]
      ]
    ],
    [
      [
        [
          "Lori"
        ],
        [
          "/wiki/Lori_FC"
        ]
      ],
      [
        [
          "Vanadzor"
        ],
        [
          "/wiki/Vanadzor"
        ]
      ],
      [
        [
          "Vanadzor Football Academy"
        ],
        [
          "/wiki/Vanadzor_Football_Academy"
        ]
      ],
      [
        [
          "880"
        ],
        [
          null
        ]
      ]
    ],
    [
      [
        [
          "Noah"
        ],
        [
          "/wiki/FC_Noah"
        ]
      ],
      [
        [
          "Yerevan",
          "Shengavit"
        ],
        [
          "/wiki/Yerevan",
          "/wiki/Shengavit_District"
        ]
      ],
      [
        [
          "Alashkert Stadium"
        ],
        [
          "/wiki/Alashkert_Stadium"
        ]
      ],
      [
        [
          "6,850"
        ],
        [
          null
        ]
      ]
    ],
    [
      [
        [
          "Pyunik"
        ],
        [
          "/wiki/FC_Pyunik"
        ]
      ],
      [
        [
          "Yerevan",
          "Kentron"
        ],
        [
          "/wiki/Yerevan",
          "/wiki/Kentron_District"
        ]
      ],
      [
        [
          "Vazgen Sargsyan Stadium"
        ],
        [
          "/wiki/Vazgen_Sargsyan_Republican_Stadium"
        ]
      ],
      [
        [
          "14,403"
        ],
        [
          null
        ]
      ]
    ],
    [
      [
        [
          "Shirak"
        ],
        [
          "/wiki/Shirak_SC"
        ]
      ],
      [
        [
          "Gyumri"
        ],
        [
          "/wiki/Gyumri"
        ]
      ],
      [
        [
          "Gyumri City Stadium"
        ],
        [
          "/wiki/Gyumri_City_Stadium"
        ]
      ],
      [
        [
          "4,500"
        ],
        [
          null
        ]
      ]
    ],
    [
      [
        [
          "Urartu"
        ],
        [
          "/wiki/FC_Urartu"
        ]
      ],
      [
        [
          "Yerevan",
          "Malatia-Sebastia"
        ],
        [
          "/wiki/Yerevan",
          "/wiki/Malatia-Sebastia_District"
        ]
      ],
      [
        [
          "Banants Stadium"
        ],
        [
          "/wiki/Urartu_Stadium"
        ]
      ],
      [
        [
          "4,860"
        ],
        [
          null
        ]
      ]
    ],
    [
      [
        [
          "Yerevan"
        ],
        [
          "/wiki/FC_Yerevan"
        ]
      ],
      [
        [
          "Vanadzor"
        ],
        [
          "/wiki/Vanadzor"
        ]
      ],
      [
        [
          "Vanadzor Football Academy"
        ],
        [
          "/wiki/Vanadzor_Football_Academy"
        ]
      ],
      [
        [
          "880"
        ],
        [
          null
        ]
      ]
    ]
  ],
  "section_title": "Teams",
  "section_text": "YerevanGandzasarLoriShirakYerevan teams : AlashkertAraratArarat-ArmeniaNoahUrartuPyunikYerevan Locations of the 2019\u201320 Armenian Premier League teams",
  "uid": "2019\u201320_Armenian_Premier_League_0",
  "intro": "The 2019-20 Armenian Premier League season is the 28th since its establishment."
}