{
  "url": "https://en.wikipedia.org/wiki/Big_Sky_Conference",
  "title": "Big Sky Conference",
  "header": [
    [
      "School",
      []
    ],
    [
      "Football stadium",
      []
    ],
    [
      "Capacity",
      []
    ],
    [
      "Basketball arena",
      []
    ],
    [
      "Capacity",
      []
    ]
  ],
  "data": [
    [
      [
        "Cal Poly",
        [
          "/wiki/Cal_Poly_Mustangs"
        ]
      ],
      [
        "Alex G. Spanos Stadium",
        [
          "/wiki/Alex_G._Spanos_Stadium"
        ]
      ],
      [
        "11,075",
        []
      ],
      [
        "Football-only member",
        []
      ],
      [
        "",
        []
      ]
    ],
    [
      [
        "Eastern Washington",
        [
          "/wiki/Eastern_Washington_Eagles"
        ]
      ],
      [
        "Roos Field",
        [
          "/wiki/Roos_Field"
        ]
      ],
      [
        "8,600",
        []
      ],
      [
        "Reese Court",
        [
          "/wiki/Reese_Court"
        ]
      ],
      [
        "6,000",
        []
      ]
    ],
    [
      [
        "Idaho",
        [
          "/wiki/Idaho_Vandals"
        ]
      ],
      [
        "Kibbie Dome",
        [
          "/wiki/Kibbie_Dome"
        ]
      ],
      [
        "16,000",
        []
      ],
      [
        "Cowan Spectrum Memorial Gymnasium",
        [
          "/wiki/Kibbie_Dome",
          "/wiki/Memorial_Gymnasium_(University_of_Idaho)"
        ]
      ],
      [
        "7,000 2,500",
        []
      ]
    ],
    [
      [
        "Idaho State",
        [
          "/wiki/Idaho_State_Bengals"
        ]
      ],
      [
        "Holt Arena",
        [
          "/wiki/Holt_Arena"
        ]
      ],
      [
        "12,000",
        []
      ],
      [
        "Holt Arena ( men ) Reed Gym ( women )",
        [
          "/wiki/Holt_Arena",
          "/wiki/Reed_Gym"
        ]
      ],
      [
        "8,000 3,040",
        []
      ]
    ],
    [
      [
        "Montana",
        [
          "/wiki/Montana_Grizzlies"
        ]
      ],
      [
        "Washington-Grizzly Stadium",
        [
          "/wiki/Washington\u2013Grizzly_Stadium"
        ]
      ],
      [
        "25,203",
        []
      ],
      [
        "Dahlberg Arena",
        [
          "/wiki/Dahlberg_Arena"
        ]
      ],
      [
        "7,321",
        []
      ]
    ],
    [
      [
        "Montana State",
        [
          "/wiki/Montana_State_Bobcats"
        ]
      ],
      [
        "Bobcat Stadium",
        [
          "/wiki/Bobcat_Stadium_(Montana_State_University)"
        ]
      ],
      [
        "20,767",
        []
      ],
      [
        "Worthington Arena",
        [
          "/wiki/Worthington_Arena"
        ]
      ],
      [
        "7,250",
        []
      ]
    ],
    [
      [
        "Northern Arizona",
        [
          "/wiki/Northern_Arizona_Lumberjacks"
        ]
      ],
      [
        "Walkup Skydome",
        [
          "/wiki/Walkup_Skydome"
        ]
      ],
      [
        "10,000",
        []
      ],
      [
        "Walkup Skydome",
        [
          "/wiki/Walkup_Skydome"
        ]
      ],
      [
        "7,000",
        []
      ]
    ],
    [
      [
        "Northern Colorado",
        [
          "/wiki/Northern_Colorado_Bears"
        ]
      ],
      [
        "Nottingham Field",
        [
          "/wiki/Nottingham_Field"
        ]
      ],
      [
        "8,533",
        []
      ],
      [
        "Bank of Colorado Arena",
        [
          "/wiki/Bank_of_Colorado_Arena"
        ]
      ],
      [
        "2,992",
        []
      ]
    ],
    [
      [
        "Portland State",
        [
          "/wiki/Portland_State_Vikings"
        ]
      ],
      [
        "Hillsboro Stadium",
        [
          "/wiki/Hillsboro_Stadium"
        ]
      ],
      [
        "7,600",
        []
      ],
      [
        "Viking Pavilion",
        [
          "/wiki/Viking_Pavilion"
        ]
      ],
      [
        "3,094",
        []
      ]
    ],
    [
      [
        "Sacramento State",
        [
          "/wiki/Sacramento_State_Hornets"
        ]
      ],
      [
        "Hornet Stadium",
        [
          "/wiki/Hornet_Stadium_(Sacramento)"
        ]
      ],
      [
        "21,195",
        []
      ],
      [
        "Hornets Nest",
        [
          "/wiki/Hornets_Nest_(Sacramento_State)"
        ]
      ],
      [
        "1,012",
        []
      ]
    ],
    [
      [
        "Southern Utah",
        [
          "/wiki/Southern_Utah_Thunderbirds"
        ]
      ],
      [
        "Eccles Coliseum",
        [
          "/wiki/Eccles_Coliseum"
        ]
      ],
      [
        "8,500",
        []
      ],
      [
        "America First Event Center",
        [
          "/wiki/America_First_Event_Center"
        ]
      ],
      [
        "5,300",
        []
      ]
    ],
    [
      [
        "UC Davis",
        [
          "/wiki/UC_Davis_Aggies"
        ]
      ],
      [
        "UC Davis Health Stadium",
        [
          "/wiki/UC_Davis_Health_Stadium"
        ]
      ],
      [
        "10,367",
        []
      ],
      [
        "Football-only member",
        []
      ],
      [
        "",
        []
      ]
    ],
    [
      [
        "Weber State",
        [
          "/wiki/Weber_State_Wildcats"
        ]
      ],
      [
        "Stewart Stadium",
        [
          "/wiki/Stewart_Stadium"
        ]
      ],
      [
        "17,500",
        []
      ],
      [
        "Dee Events Center",
        [
          "/wiki/Dee_Events_Center"
        ]
      ],
      [
        "11,500",
        []
      ]
    ]
  ],
  "section_title": "Facilities",
  "section_text": "",
  "uid": "Big_Sky_Conference_3",
  "intro": "The Big Sky Conference is a collegiate athletic conference affiliated with the NCAA's Division I, with football competing in the Football Championship Subdivision. Member institutions are located in the western United States in the nine states of Arizona, California, Colorado, Idaho, Montana, Oregon, Utah, and Washington. Four affiliate members each participate in one sport. Two schools from California are football-only participants, and two schools from the Northeast participate only in men's golf."
}