{
  "url": "https://en.wikipedia.org/wiki/List_of_football_stadiums_in_Turkey",
  "title": "List of football stadiums in Turkey",
  "header": [
    [
      [
        "Stadium"
      ],
      [
        null
      ]
    ],
    [
      [
        "Capacity"
      ],
      [
        null
      ]
    ],
    [
      [
        "City"
      ],
      [
        null
      ]
    ],
    [
      [
        "Club"
      ],
      [
        null
      ]
    ],
    [
      [
        "Opening"
      ],
      [
        null
      ]
    ]
  ],
  "data": [
    [
      [
        [
          "KozArena"
        ],
        [
          "/wiki/KozArena"
        ]
      ],
      [
        [
          "33,000"
        ],
        [
          null
        ]
      ],
      [
        [
          "Adana"
        ],
        [
          "/wiki/Adana"
        ]
      ],
      [
        [
          "Adanaspor",
          "Adana Demirspor"
        ],
        [
          "/wiki/Adanaspor",
          "/wiki/Adana_Demirspor"
        ]
      ],
      [
        [
          "2020"
        ],
        [
          null
        ]
      ]
    ],
    [
      [
        [
          "New Hatay Stadium"
        ],
        [
          null
        ]
      ],
      [
        [
          "25,000"
        ],
        [
          null
        ]
      ],
      [
        [
          "Antakya"
        ],
        [
          "/wiki/Antakya"
        ]
      ],
      [
        [
          "Hatayspor"
        ],
        [
          "/wiki/Hatayspor"
        ]
      ],
      [
        [
          "2020"
        ],
        [
          null
        ]
      ]
    ],
    [
      [
        [
          "\u00c7otanak Arena"
        ],
        [
          null
        ]
      ],
      [
        [
          "22,000"
        ],
        [
          null
        ]
      ],
      [
        [
          "Giresun"
        ],
        [
          "/wiki/Giresun"
        ]
      ],
      [
        [
          "Giresunspor"
        ],
        [
          "/wiki/Giresunspor"
        ]
      ],
      [
        [
          "2020"
        ],
        [
          null
        ]
      ]
    ],
    [
      [
        [
          "New Ordu Stadium"
        ],
        [
          null
        ]
      ],
      [
        [
          "22,000"
        ],
        [
          null
        ]
      ],
      [
        [
          "Ordu"
        ],
        [
          "/wiki/Ordu"
        ]
      ],
      [
        [
          "Yeni Orduspor"
        ],
        [
          null
        ]
      ],
      [
        [
          "2020"
        ],
        [
          null
        ]
      ]
    ],
    [
      [
        [
          "New Karaman Stadium"
        ],
        [
          null
        ]
      ],
      [
        [
          "15,000"
        ],
        [
          null
        ]
      ],
      [
        [
          "Karaman"
        ],
        [
          "/wiki/Karaman"
        ]
      ],
      [
        [
          "Karamanspor"
        ],
        [
          null
        ]
      ],
      [
        [
          "2020"
        ],
        [
          null
        ]
      ]
    ],
    [
      [
        [
          "New Alsancak Stadium"
        ],
        [
          "/wiki/\u0130zmir_Alsancak_Stadium"
        ]
      ],
      [
        [
          "15,000"
        ],
        [
          null
        ]
      ],
      [
        [
          "\u0130zmir"
        ],
        [
          "/wiki/\u0130zmir"
        ]
      ],
      [
        [
          "Altay"
        ],
        [
          "/wiki/Altay_S.K."
        ]
      ],
      [
        [
          "2020"
        ],
        [
          null
        ]
      ]
    ],
    [
      [
        [
          "New Erzincan Stadium"
        ],
        [
          null
        ]
      ],
      [
        [
          "12,500"
        ],
        [
          null
        ]
      ],
      [
        [
          "Erzincan"
        ],
        [
          "/wiki/Erzincan"
        ]
      ],
      [
        [
          "24 Erzincanspor"
        ],
        [
          null
        ]
      ],
      [
        [
          "2020"
        ],
        [
          null
        ]
      ]
    ],
    [
      [
        [
          "New Turgutlu Stadium"
        ],
        [
          "/wiki/New_Turgutlu_Stadium"
        ]
      ],
      [
        [
          "12,000"
        ],
        [
          null
        ]
      ],
      [
        [
          "Turgutlu"
        ],
        [
          "/wiki/Turgutlu"
        ]
      ],
      [
        [
          "Turgutluspor"
        ],
        [
          "/wiki/Turgutluspor"
        ]
      ],
      [
        [
          "2020"
        ],
        [
          null
        ]
      ]
    ],
    [
      [
        [
          "New Elaz\u0131\u011f Stadium"
        ],
        [
          null
        ]
      ],
      [
        [
          "18,458"
        ],
        [
          null
        ]
      ],
      [
        [
          "Elaz\u0131\u011f"
        ],
        [
          "/wiki/Elaz\u0131\u011f"
        ]
      ],
      [
        [
          "Elaz\u0131\u011fspor"
        ],
        [
          "/wiki/Elaz\u0131\u011fspor"
        ]
      ],
      [
        [
          "2021"
        ],
        [
          null
        ]
      ]
    ]
  ],
  "section_title": "Future stadiums -- Under construction",
  "section_text": "",
  "uid": "List_of_football_stadiums_in_Turkey_1",
  "intro": "This is a partial list of football stadiums in Turkey (those with a capacity of at least 10,000), ranked in order of capacity."
}