{
  "url": "https://en.wikipedia.org/wiki/MBO_Cinemas",
  "title": "MBO Cinemas",
  "header": [
    [
      [
        "Cinema"
      ],
      [
        null
      ]
    ],
    [
      [
        "Total Halls"
      ],
      [
        null
      ]
    ],
    [
      [
        "Seats"
      ],
      [
        null
      ]
    ],
    [
      [
        "Location"
      ],
      [
        null
      ]
    ],
    [
      [
        "State"
      ],
      [
        null
      ]
    ],
    [
      [
        "Remarks"
      ],
      [
        null
      ]
    ]
  ],
  "data": [
    [
      [
        [
          "Era Square Mall"
        ],
        [
          "/wiki/Era_Square"
        ]
      ],
      [
        [
          "10"
        ],
        [
          null
        ]
      ],
      [
        [
          "1,456"
        ],
        [
          null
        ]
      ],
      [
        [
          "Seremban"
        ],
        [
          "/wiki/Seremban"
        ]
      ],
      [
        [
          "Negeri Sembilan"
        ],
        [
          "/wiki/Negeri_Sembilan"
        ]
      ],
      [
        [
          "Located on Level 3"
        ],
        [
          null
        ]
      ]
    ],
    [
      [
        [
          "Melaka Mall"
        ],
        [
          null
        ]
      ],
      [
        [
          "7"
        ],
        [
          null
        ]
      ],
      [
        [
          "1,212"
        ],
        [
          null
        ]
      ],
      [
        [
          "Ayer Keroh"
        ],
        [
          "/wiki/Ayer_Keroh"
        ]
      ],
      [
        [
          "Melaka"
        ],
        [
          "/wiki/Melaka"
        ]
      ],
      [
        [
          "Located on Level 2"
        ],
        [
          null
        ]
      ]
    ],
    [
      [
        [
          "Square One Shopping Centre"
        ],
        [
          null
        ]
      ],
      [
        [
          "8"
        ],
        [
          null
        ]
      ],
      [
        [
          "1,217"
        ],
        [
          null
        ]
      ],
      [
        [
          "Batu Pahat"
        ],
        [
          "/wiki/Batu_Pahat"
        ]
      ],
      [
        [
          "Johor"
        ],
        [
          "/wiki/Johor"
        ]
      ],
      [
        [
          "Located on Level 3 . Recently renovated with new look"
        ],
        [
          null
        ]
      ]
    ],
    [
      [
        [
          "U Mall"
        ],
        [
          null
        ]
      ],
      [
        [
          "5"
        ],
        [
          null
        ]
      ],
      [
        [
          "606"
        ],
        [
          null
        ]
      ],
      [
        [
          "Skudai",
          "Johor Bahru"
        ],
        [
          "/wiki/Skudai",
          "/wiki/Johor_Bahru"
        ]
      ],
      [
        [
          "Johor"
        ],
        [
          "/wiki/Johor"
        ]
      ],
      [
        [
          "Located on Level 1"
        ],
        [
          null
        ]
      ]
    ],
    [
      [
        [
          "Heritage Mall"
        ],
        [
          null
        ]
      ],
      [
        [
          "7"
        ],
        [
          null
        ]
      ],
      [
        [
          "1,036"
        ],
        [
          null
        ]
      ],
      [
        [
          "Kota Tinggi"
        ],
        [
          "/wiki/Kota_Tinggi"
        ]
      ],
      [
        [
          "Johor"
        ],
        [
          "/wiki/Johor"
        ]
      ],
      [
        [
          "Located on Level 2"
        ],
        [
          null
        ]
      ]
    ],
    [
      [
        [
          "Kluang Mall"
        ],
        [
          null
        ]
      ],
      [
        [
          "6"
        ],
        [
          null
        ]
      ],
      [
        [
          "1,067"
        ],
        [
          null
        ]
      ],
      [
        [
          "Kluang"
        ],
        [
          "/wiki/Kluang"
        ]
      ],
      [
        [
          "Johor"
        ],
        [
          "/wiki/Johor"
        ]
      ],
      [
        [
          "Located on Level 2"
        ],
        [
          null
        ]
      ]
    ],
    [
      [
        [
          "Elements Mall"
        ],
        [
          null
        ]
      ],
      [
        [
          "10"
        ],
        [
          null
        ]
      ],
      [
        [
          "1,584"
        ],
        [
          null
        ]
      ],
      [
        [
          "Bandar Hilir"
        ],
        [
          "/wiki/Bandar_Hilir"
        ]
      ],
      [
        [
          "Melaka"
        ],
        [
          "/wiki/Melaka"
        ]
      ],
      [
        [
          "Located on Level 11 features BIG SCREEN"
        ],
        [
          null
        ]
      ]
    ],
    [
      [
        [
          "AEON Mall Bandar Dato ' Onn"
        ],
        [
          null
        ]
      ],
      [
        [
          "5"
        ],
        [
          null
        ]
      ],
      [
        [
          "663"
        ],
        [
          null
        ]
      ],
      [
        [
          "Bandar Dato ' Onn"
        ],
        [
          "/wiki/Bandar_Dato'_Onn"
        ]
      ],
      [
        [
          "Johor"
        ],
        [
          "/wiki/Johor"
        ]
      ],
      [
        [
          "Located on Level 2 features BIG SCREEN , MX4D and KECIL"
        ],
        [
          null
        ]
      ]
    ]
  ],
  "section_title": "Cinemas -- Southern Region",
  "section_text": "",
  "uid": "MBO_Cinemas_2",
  "intro": "MCAT Box Office Sdn Bhd (trading as MBO Cinemas) is a chain of cinemas in Malaysia. It is the third largest cinema chain in the country after Golden Screen Cinemas and TGV Cinemas."
}