{
  "url": "https://en.wikipedia.org/wiki/Pranavam_Arts_International",
  "title": "Pranavam Arts International",
  "header": [
    [
      [
        "Year"
      ],
      [
        null
      ]
    ],
    [
      [
        "Title"
      ],
      [
        null
      ]
    ],
    [
      [
        "Language"
      ],
      [
        null
      ]
    ]
  ],
  "data": [
    [
      [
        [
          "1993"
        ],
        [
          null
        ]
      ],
      [
        [
          "Mithunam"
        ],
        [
          "/wiki/Mithunam_(1993_film)"
        ]
      ],
      [
        [
          "Malayalam"
        ],
        [
          null
        ]
      ]
    ],
    [
      [
        [
          "1993"
        ],
        [
          null
        ]
      ],
      [
        [
          "Pudhiya Mugam"
        ],
        [
          "/wiki/Pudhiya_Mugam"
        ]
      ],
      [
        [
          "Tamil"
        ],
        [
          null
        ]
      ]
    ],
    [
      [
        [
          "1993"
        ],
        [
          null
        ]
      ],
      [
        [
          "Gandharvam"
        ],
        [
          "/wiki/Gandharvam"
        ]
      ],
      [
        [
          "Malayalam"
        ],
        [
          null
        ]
      ]
    ],
    [
      [
        [
          "1994"
        ],
        [
          null
        ]
      ],
      [
        [
          "Pingami"
        ],
        [
          "/wiki/Pingami"
        ]
      ],
      [
        [
          "Malayalam"
        ],
        [
          null
        ]
      ]
    ],
    [
      [
        [
          "1995"
        ],
        [
          null
        ]
      ],
      [
        [
          "Nirnayam"
        ],
        [
          "/wiki/Nirnayam_(1995_film)"
        ]
      ],
      [
        [
          "Malayalam"
        ],
        [
          null
        ]
      ]
    ],
    [
      [
        [
          "1996"
        ],
        [
          null
        ]
      ],
      [
        [
          "Kaalapani"
        ],
        [
          "/wiki/Kaalapani"
        ]
      ],
      [
        [
          "Malayalam"
        ],
        [
          null
        ]
      ]
    ],
    [
      [
        [
          "1997"
        ],
        [
          null
        ]
      ],
      [
        [
          "Iruvar"
        ],
        [
          "/wiki/Iruvar"
        ]
      ],
      [
        [
          "Tamil"
        ],
        [
          null
        ]
      ]
    ],
    [
      [
        [
          "1997"
        ],
        [
          null
        ]
      ],
      [
        [
          "Varnapakittu"
        ],
        [
          "/wiki/Varnapakittu"
        ]
      ],
      [
        [
          "Malayalam"
        ],
        [
          null
        ]
      ]
    ],
    [
      [
        [
          "1997"
        ],
        [
          null
        ]
      ],
      [
        [
          "Virasat"
        ],
        [
          "/wiki/Virasat_(1997_film)"
        ]
      ],
      [
        [
          "Hindi"
        ],
        [
          "/wiki/Hindi"
        ]
      ]
    ],
    [
      [
        [
          "1998"
        ],
        [
          null
        ]
      ],
      [
        [
          "Kanmadam"
        ],
        [
          "/wiki/Kanmadam"
        ]
      ],
      [
        [
          "Malayalam"
        ],
        [
          null
        ]
      ]
    ],
    [
      [
        [
          "1998"
        ],
        [
          null
        ]
      ],
      [
        [
          "Harikrishnans"
        ],
        [
          "/wiki/Harikrishnans"
        ]
      ],
      [
        [
          "Malayalam"
        ],
        [
          null
        ]
      ]
    ],
    [
      [
        [
          "1999"
        ],
        [
          null
        ]
      ],
      [
        [
          "Megham"
        ],
        [
          "/wiki/Megham"
        ]
      ],
      [
        [
          "Malayalam"
        ],
        [
          null
        ]
      ]
    ],
    [
      [
        [
          "1999"
        ],
        [
          null
        ]
      ],
      [
        [
          "Hum Dil De Chuke Sanam"
        ],
        [
          "/wiki/Hum_Dil_De_Chuke_Sanam"
        ]
      ],
      [
        [
          "Hindi"
        ],
        [
          "/wiki/Hindi"
        ]
      ]
    ],
    [
      [
        [
          "1999"
        ],
        [
          null
        ]
      ],
      [
        [
          "Olympiyan Anthony Adam"
        ],
        [
          "/wiki/Olympiyan_Anthony_Adam"
        ]
      ],
      [
        [
          "Malayalam"
        ],
        [
          null
        ]
      ]
    ],
    [
      [
        [
          "1999"
        ],
        [
          null
        ]
      ],
      [
        [
          "Vanaprastham"
        ],
        [
          "/wiki/Vanaprastham"
        ]
      ],
      [
        [
          "Malayalam"
        ],
        [
          null
        ]
      ]
    ],
    [
      [
        [
          "2000"
        ],
        [
          null
        ]
      ],
      [
        [
          "Kandukondain Kandukondain"
        ],
        [
          "/wiki/Kandukondain_Kandukondain"
        ]
      ],
      [
        [
          "Tamil"
        ],
        [
          null
        ]
      ]
    ]
  ],
  "section_title": "Pranamam Pictures",
  "section_text": "Mohanlal distributed films in Kerala under the company Panamam Pictures .",
  "uid": "Pranavam_Arts_0",
  "intro": "Pranavam Arts International (formerly Pranavam Arts) is a film production and distribution company founded in 1990 by Indian actor Mohanlal. Since then the company has produced a total of 11 films."
}